loki_logger_async/__init__.py
loki_logger_async/aiohttp_session.py
loki_logger_async/config.py
loki_logger_async/flush_manager.py
loki_logger_async/loki_logger.py
loki_logger_async/types.py
loki_logger_async/utils.py
loki_logger_async/interceptors/__init__.py
loki_logger_async/interceptors/console.py
loki_logger_async/interceptors/exceptions.py
loki_logger_async/interceptors/logging.py
loki_logger_async-1.0.6.dist-info/METADATA
loki_logger_async-1.0.6.dist-info/WHEEL
loki_logger_async-1.0.6.dist-info/RECORD
