Metadata-Version: 2.4
Name: loki-logger-async
Version: 1.0.6
Summary: Ultra-performant Loki logger for Python applications (asyncio + aiohttp)
Project-URL: Homepage, https://github.com/elvenobservability/loki-logger-async
Project-URL: Bug Tracker, https://github.com/elvenobservability/loki-logger-async/issues
Author-email: Leonardo Zwirtes <leonardo.zwirtes@elven.works>
License: MIT
Keywords: aiohttp,asyncio,grafana,logging,loki,observability
Classifier: License :: OSI Approved :: MIT License
Classifier: Operating System :: OS Independent
Classifier: Programming Language :: Python :: 3
Requires-Python: >=3.9
